SheetCode/Formatters.py
SheetCode/Scripts.py
SheetCode/Sheet.py
SheetCode/Summary.py
SheetCode/Traceability.py
SheetCode/__init__.py
sheetcode-0.0.25.dist-info/METADATA
sheetcode-0.0.25.dist-info/WHEEL
sheetcode-0.0.25.dist-info/licenses/LICENSE
sheetcode-0.0.25.dist-info/RECORD
